vae2/__init__.py
vae2/vae.py
vae2-0.2.dist-info/LICENSE
vae2-0.2.dist-info/METADATA
vae2-0.2.dist-info/WHEEL
vae2-0.2.dist-info/top_level.txt
vae2-0.2.dist-info/RECORD
