Metadata-Version: 2.1
Name: vae2
Version: 0.2
Summary: A VAE MNIST package
Home-page: UNKNOWN
Author: Shuvam Ghosal
Author-email: shuvamghosal98@gmail.com
License: MIT
Platform: UNKNOWN
Classifier: Programming Language :: Python :: 2
Classifier: License :: OSI Approved :: MIT License
Classifier: Operating System :: OS Independent
